.DS_Store
kwtools/.DS_Store
kwtools/__init__.py
kwtools/_version.py
kwtools/settings.py
kwtools/box/__init__.py
kwtools/config/__init__.py
kwtools/configs/__init__.py
kwtools/lib/__init__.py
kwtools/scripts/__init__.py
kwtools/scripts/wyy.py
kwtools/tools1/.utils_plot.py.un~
kwtools/tools1/__init__.py
kwtools/tools1/util_ocr.py
kwtools/tools1/utils_crawl.py
kwtools/tools1/utils_email.py
kwtools/tools1/utils_encrypt.py
kwtools/tools1/utils_img.py
kwtools/tools1/utils_pandas.py
kwtools/tools1/utils_plot.py
kwtools/tools1/utils_python.py
kwtools/tools1/utils_qrcode.py
kwtools/tools1/utils_redis.py
kwtools/tools1/utils_requests.py
kwtools/tools2/__init__.py
kwtools/tools2/utils_pandas.py
kwtools/tools2/utils_python.py
kwtools/tools2/utils_requests.py
kwtools/ttt/__init__.py
kwtools/ttt/t1.py
kwtools-0.1.6.dist-info/LICENSE
kwtools-0.1.6.dist-info/METADATA
kwtools-0.1.6.dist-info/WHEEL
kwtools-0.1.6.dist-info/top_level.txt
kwtools-0.1.6.dist-info/RECORD
