Metadata-Version: 2.1
Name: kwtools
Version: 0.1.6
Summary: integrated commonly used third-party libraries to personal use
Home-page: https://github.com/kerwin6182828/kwtools
Author: Kerwin Lui
Author-email: kerwin19950830@gmail.com
License: MIT
Platform: UNKNOWN
Classifier: Development Status :: 4 - Beta
Classifier: License :: OSI Approved :: MIT License
Classifier: Programming Language :: Python
Classifier: Programming Language :: Python :: 3.6
Classifier: Programming Language :: Python :: 3.7
Classifier: Programming Language :: Python :: 3.8
Classifier: Topic :: Software Development :: Libraries
Classifier: Topic :: Software Development :: Libraries :: Python Modules
Classifier: Intended Audience :: Developers
Requires-Python: >=3.6
Requires-Dist: retry
Requires-Dist: pysnooper
Requires-Dist: user-agent
Requires-Dist: requests
Requires-Dist: uuid
Requires-Dist: exchangelib
Requires-Dist: urllib3
Requires-Dist: schedule
Requires-Dist: websocket
Requires-Dist: PyExecJS
Requires-Dist: aiohttp
Requires-Dist: numpy
Requires-Dist: pandas
Requires-Dist: xlsxwriter
Requires-Dist: pymongo
Requires-Dist: redis
Requires-Dist: pymysql
Requires-Dist: sqlalchemy
Requires-Dist: pycryptodome
